AUTHORS.rst
CONTRIBUTING.rst
HISTORY.rst
LICENSE
MANIFEST.in
README.rst
setup.cfg
setup.py
XsTools.egg-info/PKG-INFO
XsTools.egg-info/SOURCES.txt
XsTools.egg-info/dependency_links.txt
XsTools.egg-info/entry_points.txt
XsTools.egg-info/not-zip-safe
XsTools.egg-info/pbr.json
XsTools.egg-info/requires.txt
XsTools.egg-info/top_level.txt
docs/Makefile
docs/authors.rst
docs/conf.py
docs/contributing.rst
docs/history.rst
docs/index.rst
docs/installation.rst
docs/make.bat
docs/readme.rst
docs/usage.rst
tests/__init__.py
tests/test_xsconnect.py
xstools/81-xstools-usb.rules
xstools/XstoolsApi.py
xstools/__init__.py
xstools/flashdev.py
xstools/gxstools.py
xstools/picmicro.py
xstools/ramdev.py
xstools/usb2serial.py
xstools/xilbitstr.py
xstools/xilfpga.py
xstools/xsbitarray.py
xstools/xsboard.py
xstools/xscomm.py
xstools/xsdutio.py
xstools/xserror.py
xstools/xsflags.py
xstools/xshostio.py
xstools/xsi2c.py
xstools/xsjtag.py
xstools/xsload.py
xstools/xsmemio.py
xstools/xsspi.py
xstools/xstest.py
xstools/xsusb.py
xstools/xsusbprg.py
xstools/icons/down_arrow.png
xstools/icons/down_arrow_disabled.png
xstools/icons/fpga.png
xstools/icons/sdram.png
xstools/icons/serial_flash.png
xstools/icons/uc.png
xstools/test/__init__.py
xstools/test/test_location.py
xstools/test/test_utils.py
xstools/xula/XuLA_jtag.hex
xstools/xula/fintf_jtag_200.bit
xstools/xula/fintf_jtag_50.bit
xstools/xula/ramintfc_jtag_200.bit
xstools/xula/ramintfc_jtag_50.bit
xstools/xula/test_board_jtag_200.bit
xstools/xula/test_board_jtag_50.bit
xstools/xula2/XuLA_jtag.hex
xstools/xula2/fintf_jtag_lx25.bit
xstools/xula2/fintf_jtag_lx9.bit
xstools/xula2/ramintfc_jtag_lx25.bit
xstools/xula2/ramintfc_jtag_lx9.bit
xstools/xula2/test_board_jtag_lx25.bit
xstools/xula2/test_board_jtag_lx9.bit