Metadata-Version: 1.1
Name: XsTools
Version: 0.1.28
Summary: Tools and classes for interfacing with XESS FPGA boards via USB.
Home-page: https://github.com/xesscorp/XSTOOLs
Author: XESS Corporation
Author-email: info@xess.com
License: GPLv2+
Keywords: xstools
Platform: UNKNOWN
Classifier: Development Status :: 2 - Pre-Alpha
Classifier: Intended Audience :: Developers
Classifier: License :: OSI Approved :: GNU General Public License v2 or later (GPLv2+)
Classifier: Natural Language :: English
Classifier: Programming Language :: Python :: 2
Classifier: Programming Language :: Python :: 2.6
Classifier: Programming Language :: Python :: 2.7
